primer3plus/__init__.py
primer3plus/__version__.py
primer3plus/constants.py
primer3plus/design/__init__.py
primer3plus/design/interfaces.py
primer3plus/design/results.py
primer3plus/exceptions.py
primer3plus/log.py
primer3plus/params/__init__.py
primer3plus/params/expected_opts.py
primer3plus/primer3_params_raw.txt
primer3plus/utils/__init__.py
primer3plus-1.0.8.dist-info/WHEEL
primer3plus-1.0.8.dist-info/METADATA
primer3plus-1.0.8.dist-info/RECORD
