Metadata-Version: 2.1
Name: primer3plus
Version: 1.0.8
Summary: An easy-to-use Python API for Primer3 primer design.
Home-page: https://github.com/jvrana/primer3-py-plus
License: MIT
Author: Justin Vrana
Author-email: justin.vrana@gmail.com
Requires-Python: >=3.5,<4.0
Classifier: Development Status :: 4 - Beta
Classifier: Intended Audience :: Science/Research
Classifier: License :: OSI Approved :: MIT License
Classifier: Programming Language :: Python :: 3
Classifier: Programming Language :: Python :: 3.5
Classifier: Programming Language :: Python :: 3.6
Classifier: Programming Language :: Python :: 3.7
Classifier: Topic :: Scientific/Engineering :: Bio-Informatics
Requires-Dist: loggable-jdv (>=0.1.2,<0.2.0)
Requires-Dist: primer3-py (>=0.6.0,<0.7.0)
Project-URL: Documentation, https://jvrana.github.io/primer3-py-plus/
